<?xml version="1.0" encoding="utf-8"?>
<!-- c:\temp\AS2Go -->
<Config>
  <Scripts>
    <Script Name="Name" Value="AS2Go" />
    <Script Name="Version" Value="2.8" />
    <Script Name="Author" Value="me@mrhozi.com" />
  </Scripts>
  <DefaultParameter>
    <!-- Use Case -->
    <Setting Name="UseCase" Value="Attack scenario to GO" />
    <Setting Name="DemoTitle" Value="Attack scenario to GO - along the kill-chain" />
    <!-- Domain Setting - automatically filled -->
    <Setting Name="mydc" Value="[filled automatically]" />
    <Setting Name="myViPC" Value="[filled automatically]" />
    <Setting Name="fqdn" Value="[filled automatically]" />
    <Setting Name="DomainSID" Value="[filled automatically]" />
    <!-- Domain Setting - Changes are required -->
    <Setting Name="mySAW" Value="[your AdminPC]" />
    <Setting Name="myAppServer" Value="[your DC or AdminPC]" />
    <Setting Name="BDUsersOU" Value="[CN=Users,DC=xxx,DC=xxx]" />
    <Setting Name="MySearchBase" Value="[OU=Demo Accounts,OU=AS2Go,DC=xxx,DC=xxx]" />
    <Setting Name="OfflineDITFile" Value=" [\\Your server\AD-Backup]" />
    <Setting Name="globalHelpDesk" Value="SG-AS2Go-Helpdesk" />
    <!-- MDI Setting - Changes are required -->
    <Setting Name="Honeytoken" Value="me@mrhozi.com" />
    <!-- Need for Latermovement - Changes are required -->
    <Setting Name="pthntml" Value="[value can be set during the attack]" />
    <Setting Name="krbtgtntml" Value="[value can be set during the attack]" />
    <!-- do NOT change these parameter needed for PtT -->
    <Setting Name="ticketsDir" Value="C:\temp\tickets" />
    <Setting Name="ticketsPath" Value="c$\temp\tickets" />
    <!-- Parameter -->
    <Setting Name="time2reboot" Value="30" />
    <Setting Name="OpenSSL" Value="C:\Program Files\OpenSSL-Win64\start.bat" />
    <Setting Name="EnterpriseCA" Value="ROOT-DC22-01.WS22-ROOT.CORP\WS22-ROOT-ROOT-DC22-01-CA" />
    <Setting Name="BadCA" Value="AS2GoBadCert" />
    <!-- Spare part -->
    <Setting Name="SP01" Value="xxx" />
    <Setting Name="SP02" Value="xxx" />
    <Setting Name="SP03" Value="xxx" />
    <Setting Name="SP04" Value="xxx" />
    <Setting Name="SP05" Value="xxx" />
    <Setting Name="SP06" Value="xxx" />
    <Setting Name="SP07" Value="xxx" />
    <Setting Name="SP08" Value="xxx" />
    <!-- no need for modification -->
    <Setting Name="LastStart" Value="2023-04-13 19:50:25" />
    <Setting Name="LastFinished" Value="2023-03-30 15:15:55" />
    <Setting Name="LastDuration" Value="00:14:38 [h]" />
    <Setting Name="LastVictim" Value="VI-HERRHOZI" />
    <Setting Name="LastBDUser" Value="BD-20230412.104134" />
    <Setting Name="LastStage" Value="Privilege Escalation" />
    <Setting Name="LastPW" Value="xxxxxxxx" />
    <Setting Name="LastNumofDemoUsers" Value="50" />
    <Setting Name="LastIdentifier" Value="168128893223735" />
    <Setting Name="LastGTUser" Value="FU-20230414.182600" />
    <Setting Name="LastPriviledgeEscaltion" Value="AS2GoBadCert" />
  </DefaultParameter>
</Config>